reasoner_validator/__init__.py
reasoner_validator/biolink/__init__.py
reasoner_validator/biolink/ontology.py
reasoner_validator/codes.yaml
reasoner_validator/github.py
reasoner_validator/message.py
reasoner_validator/report.py
reasoner_validator/trapi/__init__.py
reasoner_validator/trapi/mapping.py
reasoner_validator/validation_codes.py
reasoner_validator/validator.py
reasoner_validator/versioning.py
reasoner_validator/versions.yaml
reasoner_validator-6.0.1.dist-info/METADATA
reasoner_validator-6.0.1.dist-info/WHEEL
reasoner_validator-6.0.1.dist-info/licenses/LICENSE
reasoner_validator-6.0.1.dist-info/RECORD
