Metadata-Version: 2.4
Name: reasoner-validator
Version: 6.0.1
Summary: Validation tools for Reasoner API
License: MIT
License-File: LICENSE
Keywords: NCATS,Biomedical Data Translator,Translator,ReasonerAPI,TRAPI,validation,Biolink Model
Author: Richard Bruskiewich
Author-email: richard.bruskiewich@delphinai.com
Maintainer: Richard Bruskiewich
Maintainer-email: richard.bruskiewich@delphinai.com
Requires-Python: >=3.10,<3.13
Classifier: Intended Audience :: Science/Research
Classifier: License :: OSI Approved :: MIT License
Classifier: Operating System :: OS Independent
Classifier: Programming Language :: Python :: 3
Classifier: Programming Language :: Python :: 3.10
Classifier: Programming Language :: Python :: 3.11
Classifier: Programming Language :: Python :: 3.12
Classifier: Topic :: Scientific/Engineering :: Bio-Informatics
Requires-Dist: PyYAML (>=6.0,<7.0)
Requires-Dist: biolink-model (>=4.3.6,<5.0.0)
Requires-Dist: bioregistry (>=0.12.46,<0.13.0)
Requires-Dist: bmt (==1.4.6)
Requires-Dist: dictdiffer (>=0.9.0,<0.10.0)
Requires-Dist: jsonschema (>=4.24.0,<5.0.0)
Requires-Dist: poetry-core (>=2.1.3,<3.0.0)
Requires-Dist: pydantic (>=2,<3)
Requires-Dist: requests (>=2.28.1,<3.0.0)
Requires-Dist: urllib3 (>=2.5.0,<3.0.0)
Project-URL: Bug Tracker, https://github.com/NCATSTranslator/reasoner-validator/issues
Project-URL: Change Log, https://github.com/NCATSTranslator/reasoner-validator/blob/master/CHANGELOG.md
Project-URL: Documentation, https://ncatstranslator.github.io/reasoner-validator/
Project-URL: Homepage, https://github.com/NCATSTranslator
Project-URL: Repository, https://github.com/NCATSTranslator/reasoner-validator
